README.md
keycut/__init__.py
keycut/__main__.py
keycut/cli.py
keycut/load.py
keycut/render.py
keycut/search.py
keycut/ui.py
keycut/utils.py
keycut/watch.py
pyproject.toml
keycut-0.3.0.dist-info/entry_points.txt
keycut-0.3.0.dist-info/LICENSE
keycut-0.3.0.dist-info/WHEEL
keycut-0.3.0.dist-info/METADATA
keycut-0.3.0.dist-info/RECORD
